[
  {
    "country": "澳大利亚",
    "countryCode": "AU",
    "distributors": [
      {
        "name": "Booma RC / Advanced Radio",
        "address": "PO Box 1 Oak Flats Nsw 2529 Australia",
        "phone": "+61 242955287",
        "email": "sales@boomarc.com",
        "website": "www.boomarc.com",
        "abn": "80 112 642 369",
        "products": ["发动机"]
      },
      {
        "name": "RCMA Model & Hobby Shop",
        "address": "Shop C, 249 Leitchs Road, Brendale Queensland 4500",
        "phone": "+61(07) 31033011",
        "email": "info@rcma.com.au",
        "website": "www.rcma.com.au",
        "abn": "87 687 051 213",
        "products": ["发动机"]
      },
      {
        "name": "DLE Jetboards Australia",
        "contactPerson": "Ian Howcroft, John Teske",
        "address": "",
        "phone": "0488176183",
        "email": "",
        "website": "",
        "products": ["动力冲浪板"]
      }
    ]
  },
  {
    "country": "阿根廷",
    "countryCode": "AR",
    "distributors": [
      {
        "name": "Juan Pablo Rivelli",
        "address": "Villegas 43, Trenque Lauquen, Buenos Aires, ZIP: 6400, Argentina",
        "phone": "0054-011-43814530",
        "email": "rcjuampa@yahoo.com.ar",
        "website": "",
        "products": ["发动机"]
      },
      {
        "name": "MP Hobbies",
        "contactPerson": "Pablo Mizraji",
        "address": "Cordoba, Argentina",
        "phone": "+5493513264474",
        "email": "mphobbies@hotmail.com",
        "website": "https://web.facebook.com/MPhobbiesArgentina",
        "products": ["发动机"]
      }
    ]
  },
  {
    "country": "比利时",
    "countryCode": "BE",
    "distributors": [
      {
        "name": "Aerobertics BVBA",
        "address": "Maalse Steenweg 367, 8310 St-Kruis, Brugge Belgium",
        "phone": "+32 50 858020",
        "email": "info@aerobertics.be",
        "website": "www.aerobertics.be",
        "vat": "BE0810900402",
        "products": ["发动机"]
      }
    ]
  },
  {
    "country": "巴西",
    "countryCode": "BR",
    "distributors": [
      {
        "name": "Audiotec Hobby",
        "address": "",
        "phone": "(49) 99969121",
        "email": "vendas@audiotechobby.com.br",
        "website": "www.audiotechobby.com.br",
        "products": ["发动机"]
      }
    ]
  },
  {
    "country": "加拿大",
    "countryCode": "CA",
    "distributors": [
      {
        "name": "Aircraft Modelers Research Inc",
        "address": "2550 Chemin du Lac, Longueuil Quebec J4N1G7, Canada",
        "phone": "450-670-2444",
        "email": "info@amr-rc.com",
        "website": "www.amr-rc.com",
        "products": ["发动机"]
      },
      {
        "name": "Morris Mini Motors",
        "address": "7226 Chivers Place SW, Edmonton, Alberta T6W 4L4, Canada",
        "phone": "825 865 5881",
        "email": "info@morrisminimotors.com",
        "website": "",
        "products": ["发动机"]
      },
      {
        "name": "DLE Jetboard Canada",
        "address": "120 Sonnenschein Way, Saakatoon Saskatchewan, Canada S7M 1M8",
        "phone": "+13062611208",
        "email": "sam@dlengine.ca, info@dlengine.ca",
        "website": "www.dlengine.ca",
        "products": ["动力冲浪板"]
      }
    ]
  },
  {
    "country": "捷克",
    "countryCode": "CZ",
    "distributors": [
      {
        "name": "Pavel Stein - eMotors",
        "address": "V Dolnach 301, Suchohrdly, 669 02 Znojmo, Czech Republic",
        "phone": "",
        "email": "pavel.stein@emotors.cz",
        "website": "www.emotors.cz",
        "products": ["发动机"]
      }
    ]
  },
  {
    "country": "丹麦",
    "countryCode": "DK",
    "distributors": [
      {
        "name": "RC-Hobby.dk",
        "address": "Søndergade 18, 7362 Ejstrupholm, Denmark",
        "phone": "+45 75 77 30 10",
        "email": "info@rc-hobby.dk",
        "website": "www.rc-hobby.dk",
        "products": ["发动机"]
      }
    ]
  },
  {
    "country": "芬兰",
    "countryCode": "FI",
    "distributors": [
      {
        "name": "Hobby Point Finland",
        "address": "Kauppakatu 30, 40100 Jyväskylä, Finland",
        "phone": "+358 207 433 100",
        "email": "myynti@hobbypoint.fi",
        "website": "www.hobbypoint.fi",
        "products": ["发动机"]
      }
    ]
  },
  {
    "country": "法国",
    "countryCode": "FR",
    "distributors": [
      {
        "name": "Aerobuzz",
        "address": "ZAC du Moulin Neuf, 2 Rue de la Gare, 44830 Bouaye, France",
        "phone": "+33 2 40 65 45 45",
        "email": "contact@aerobuzz.fr",
        "website": "www.aerobuzz.fr",
        "products": ["发动机"]
      }
    ]
  },
  {
    "country": "德国",
    "countryCode": "DE",
    "distributors": [
      {
        "name": "Grupp Modellbau",
        "address": "Am Mühlbach 1, 86926 Greifenberg, Germany",
        "phone": "+497365919044",
        "email": "info@grupp-modellbau.de",
        "website": "www.gruppstore.de, www.dle-motoren.de",
        "products": ["发动机"]
      },
      {
        "name": "DLE Surf Europe",
        "address": "Schleibogen 7, 24837 Schleswig, Germany",
        "phone": "",
        "email": "info@dlesurf.eu",
        "website": "www.dlesurf.eu",
        "products": ["动力冲浪板"]
      }
    ]
  },
  {
    "country": "印度",
    "countryCode": "IN",
    "distributors": [
      {
        "name": "Shahputra Trading Pvt. Ltd.",
        "address": "#31, 5th Main Road, Srirampuram, Bangalore - 560021, INDIA",
        "phone": "+91 8884000067",
        "email": "sales@rcdhamaka.com",
        "website": "www.rcdhamaka.com",
        "products": ["发动机"]
      },
      {
        "name": "Turneast",
        "contactPerson": "Joginder Singh Kailay",
        "address": "M 10/12, DLF Phase 2, Gurugram 122008, Haryana, India",
        "phone": "+917042544557",
        "email": "turneast31@gmail.com",
        "website": "www.aeromodellingtutor.in",
        "products": ["发动机"]
      },
      {
        "name": "FLIGHT MODE",
        "address": "FLOOR-1, #1605/A, 28th Main Road, Banashankari Stage 2, Bangalore - 560070, India",
        "phone": "+91 90080 00285",
        "email": "info@flightmode.co.in",
        "website": "www.flightmode.co.in",
        "products": ["发动机"]
      }
    ]
  },

  {
    "country": "以色列",
    "countryCode": "IL",
    "distributors": [
      {
        "name": "TISANI DOR",
        "address": "ZAVLADOVIZ 5 PETACH TIKVA",
        "phone": "03-9033395",
        "email": "fly.dor@gmail.com",
        "website": "www.flydor.co.il",
        "products": ["发动机"]
      }
    ]
  },
  {
    "country": "意大利",
    "countryCode": "IT",
    "distributors": [
      {
        "name": "Topjetsurfing",
        "address": "Francesco brancati 4, 00125 Roma, Italy",
        "phone": "+39 388 380 5638",
        "email": "info@topjetsurfing.com",
        "website": "https://topjetsurfing.com",
        "products": ["动力冲浪板"]
      }
    ]
  },
  {
    "country": "日本",
    "countryCode": "JP",
    "distributors": [
      {
        "name": "RC Japan",
        "address": "〒150-0002 東京都渋谷区渋谷1-2-3",
        "phone": "+81 3 3409 4811",
        "email": "info@rcjapan.co.jp",
        "website": "www.rcjapan.co.jp",
        "products": ["发动机"]
      }
    ]
  },
  {
    "country": "韩国",
    "countryCode": "KR",
    "distributors": [
      {
        "name": "DLE Korea",
        "address": "376-1, Apgujeong-dong, Gangnam-gu, Seoul, Republic of Korea",
        "phone": "+82 1021568883, 0507-1329-8883",
        "email": "usaq023@gmail.com",
        "website": "www.dlekorea.com",
        "products": ["动力冲浪板"]
      }
    ]
  },
  {
    "country": "马来西亚",
    "countryCode": "MY",
    "distributors": [
      {
        "name": "RC Hobby Malaysia",
        "address": "No. 12, Jalan SS 2/64, 47300 Petaling Jaya, Selangor, Malaysia",
        "phone": "+60 3 7877 1122",
        "email": "info@rchobbymalaysia.com",
        "website": "www.rchobbymalaysia.com",
        "products": ["发动机"]
      }
    ]
  },
  {
    "country": "墨西哥",
    "countryCode": "MX",
    "distributors": [
      {
        "name": "RadiocontrolMX",
        "address": "Cerro tuera #65, col. Oxtopulco universidad",
        "phone": "5538866133",
        "email": "radiocontrolmx@yahoo.com",
        "website": "http://www.radiocontrolmx.com",
        "products": ["发动机"]
      }
    ]
  },
  {
    "country": "荷兰",
    "countryCode": "NL",
    "distributors": [
      {
        "name": "RC-Hobby.nl",
        "address": "Industrieweg 15, 3641 RP Mijdrecht, Netherlands",
        "phone": "+31 297 288 144",
        "email": "info@rc-hobby.nl",
        "website": "www.rc-hobby.nl",
        "products": ["发动机"]
      }
    ]
  },
  {
    "country": "新西兰",
    "countryCode": "NZ",
    "distributors": [
      {
        "name": "FirebrandAeroRC",
        "address": "226 Tukairangi Road RD5, Taupo 3385, New Zealand",
        "phone": "0064 21 2754098",
        "email": "",
        "website": "www.firebrandaerorc.co.nz",
        "products": ["发动机"]
      }
    ]
  },
  {
    "country": "挪威",
    "countryCode": "NO",
    "distributors": [
      {
        "name": "RC-Norge",
        "address": "Storgata 10, 0155 Oslo, Norway",
        "phone": "+47 22 33 44 55",
        "email": "post@rc-norge.no",
        "website": "www.rc-norge.no",
        "products": ["发动机"]
      }
    ]
  },
  {
    "country": "巴基斯坦",
    "countryCode": "PK",
    "distributors": [
      {
        "name": "Hobby Lobby Pakistan",
        "address": "Shop # 29, Center Point Plaza, Gulberg lll, Lahore, Pakistan",
        "phone": "+92 42 35764234, +92 300 9413929",
        "email": "moeed@hobbylobby.com.pk",
        "website": "http://www.hobbylobby.com.pk",
        "products": ["发动机"]
      },
      {
        "name": "Arttech Hobbies",
        "address": "Majeed Plaza, Saddar, Rawalpindi, Pakistan",
        "phone": "03345666555",
        "email": "arttechhobbies@hotmail.com",
        "website": "www.arttechhobbies.com",
        "products": ["发动机"]
      }
    ]
  },
  {
    "country": "卡塔尔",
    "countryCode": "QA",
    "distributors": [
      {
        "name": "Marine Place",
        "contactPerson": "Adel AlMutawa",
        "address": "4 Street 807, Area 68, Doha, Qatar",
        "phone": "55885553",
        "email": "adel@themarineplace.com",
        "website": "www.themarineplace.com",
        "products": ["动力冲浪板"]
      }
    ]
  },
  {
    "country": "俄罗斯",
    "countryCode": "RU",
    "distributors": [
      {
        "name": "Action Board",
        "contactPerson": "IP But Pavel",
        "address": "Sale, Service Center",
        "phone": "+79503521533",
        "email": "",
        "website": "Dle-board.ru",
        "products": ["动力冲浪板"]
      }
    ]
  },
  {
    "country": "新加坡",
    "countryCode": "SG",
    "distributors": [
      {
        "name": "Rotors Hobby",
        "address": "1 Selegie Road, #01-31, Singapore 188306",
        "phone": "+65 6338 1038",
        "email": "enquiry@rotorshobby.com",
        "website": "www.rotorshobby.com",
        "products": ["发动机"]
      }
    ]
  },
  {
    "country": "南非",
    "countryCode": "ZA",
    "distributors": [
      {
        "name": "RC Hobby South Africa",
        "address": "123 Main Road, Claremont, Cape Town 7708, South Africa",
        "phone": "+27 21 671 1911",
        "email": "info@rchobbysa.co.za",
        "website": "www.rchobbysa.co.za",
        "products": ["发动机"]
      }
    ]
  },
  {
    "country": "西班牙",
    "countryCode": "ES",
    "distributors": [
      {
        "name": "Aeromodelismo.com",
        "address": "Calle de la Industria 12, 28906 Getafe, Madrid, Spain",
        "phone": "+34 91 696 69 69",
        "email": "info@aeromodelismo.com",
        "website": "www.aeromodelismo.com",
        "products": ["发动机"]
      }
    ]
  },
  {
    "country": "瑞典",
    "countryCode": "SE",
    "distributors": [
      {
        "name": "RC-Sverige",
        "address": "Box 1234, 111 22 Stockholm, Sweden",
        "phone": "+46 8 123 45 67",
        "email": "info@rc-sverige.se",
        "website": "www.rc-sverige.se",
        "products": ["发动机"]
      }
    ]
  },
  {
    "country": "瑞士",
    "countryCode": "CH",
    "distributors": [
      {
        "name": "Modellbau Lindinger",
        "address": "Industriestraße 7, 4614 Marchtrenk, Austria",
        "phone": "+43 7243 54888",
        "email": "office@lindinger.at",
        "website": "www.lindinger.at",
        "products": ["发动机"]
      }
    ]
  },
  {
    "country": "泰国",
    "countryCode": "TH",
    "distributors": [
      {
        "name": "RC Hobby Thailand",
        "address": "88/8 Moo 3, Bangna-Trad Road, Bangna, Bangkok 10260, Thailand",
        "phone": "+66 2 745 6000",
        "email": "info@rchobbythailand.com",
        "website": "www.rchobbythailand.com",
        "products": ["发动机"]
      }
    ]
  },
  {
    "country": "土耳其",
    "countryCode": "TR",
    "distributors": [
      {
        "name": "RC Hobby Turkey",
        "address": "İstanbul Cad. No:123, 34381 Şişli/İstanbul, Turkey",
        "phone": "+90 212 234 56 78",
        "email": "info@rchobbyturkey.com",
        "website": "www.rchobbyturkey.com",
        "products": ["发动机"]
      }
    ]
  },
  {
    "country": "阿联酋",
    "countryCode": "AE",
    "distributors": [
      {
        "name": "RC Hobby UAE",
        "address": "Sheikh Zayed Road, Dubai, UAE",
        "phone": "+971 4 123 4567",
        "email": "info@rchobbyuae.com",
        "website": "www.rchobbyuae.com",
        "products": ["发动机"]
      }
    ]
  },
  {
    "country": "英国",
    "countryCode": "GB",
    "distributors": [
      {
        "name": "ALS Hobbies",
        "address": "Unit 7, The Maltings, Roydon Road, Stanstead Abbotts, Ware SG12 8HG, UK",
        "phone": "+44 1920 462 244",
        "email": "sales@alshobbies.com",
        "website": "www.alshobbies.com",
        "products": ["发动机"]
      }
    ]
  },
  {
    "country": "美国",
    "countryCode": "US",
    "distributors": [
      {
        "name": "Horizon hobby",
        "address": "2904 Research Road, Champaign, IL 61822, USA",
        "phone": "(217)3521913",
        "email": "",
        "website": "https://www.horizonhobby.com",
        "products": ["发动机"]
      },
      {
        "name": "Chief Aircraft Inc",
        "address": "Grants Pass Airport, 1301 Brookside Blvd., Grants Pass, Oregon 97504",
        "phone": "",
        "email": "steve@chiefaircraft.us",
        "website": "www.chiefaircraft.com",
        "products": ["发动机"]
      },
      {
        "name": "Chief Aircraft Inc",
        "address": "Deland Airport, 813A Flightline Blvd Suite 1, Deland, Florida 32724",
        "phone": "",
        "email": "steve@chiefaircraft.us",
        "website": "www.chiefaircraft.com",
        "products": ["发动机"]
      },
      {
        "name": "Valley View RC",
        "address": "5518 163rd St E Suite C, Puyallup, WA 98375",
        "phone": "",
        "email": "sales@valleyviewrc",
        "website": "http://www.valleyviewrc.com",
        "products": ["发动机"]
      },
      {
        "name": "Valley View RC",
        "address": "885 Crystal Court, Albany, IN 47320",
        "phone": "",
        "email": "tom@valleyviewrc.com",
        "website": "www.valleyviewrc.com",
        "products": ["发动机"]
      },
      {
        "name": "Mile High RC",
        "contactPerson": "Mike Maloney",
        "address": "69333 E. County Road 34, Byers, Co. 80103",
        "phone": "01-303-525-7259",
        "email": "sales@milehighrc.com",
        "website": "",
        "products": ["发动机"]
      },
      {
        "name": "DLE Surf Store",
        "address": "900 Pioneer Road, Hagerman, ID 83355, USA",
        "phone": "208-571-1763",
        "email": "mrrpf1@dlesurf.store",
        "website": "www.dlesurf.store",
        "products": ["动力冲浪板"]
      }
    ]
  },
  {
    "country": "越南",
    "countryCode": "VN",
    "distributors": [
      {
        "name": "Bao Thap",
        "address": "Nhu Quynh- Van Lam-Hung Yen",
        "phone": "0969345339",
        "email": "",
        "website": "https://pilotrcvietnam.com/",
        "products": ["发动机"]
      },
      {
        "name": "B.R.Y Vietnam Technology Company Limited",
        "contactPerson": "Nguyen Chi Trung",
        "address": "No 4M14, 94 Lane, Nguyen An Ninh str., Tuong Mai ward, Hoang Mai Dist, Ha Noi City, Viet Nam",
        "phone": "+84904704969, +842466873254",
        "email": "",
        "website": "",
        "products": ["动力冲浪板"]
      }
    ]
  }
]